watcher/__init__.py
watcher/dispatcher.py
watcher/updaters.py
watcher/watcher.py
watcher/events/__init__.py
watcher/events/event.py
watcher/events/quora.py
profile_watcher-1.0.0.dist-info/LICENSE
profile_watcher-1.0.0.dist-info/METADATA
profile_watcher-1.0.0.dist-info/WHEEL
profile_watcher-1.0.0.dist-info/top_level.txt
profile_watcher-1.0.0.dist-info/RECORD
