Metadata-Version: 2.1
Name: profile-watcher
Version: 1.0.0
Summary: Get updates when anything change in any social media profile.
Home-page: https://github.com/TheShubhendra/profile-watcher
Author: Shubhendra Kushwaha
Author-email: shubhendrakushwaha94@gmail.com
License: GNU-AGPL
Keywords: social media,quora
Platform: UNKNOWN
Classifier: Development Status :: 4 - Beta
Classifier: Environment :: Console
Classifier: Intended Audience :: Developers
Classifier: Topic :: Software Development :: Build Tools
Classifier: License :: Free For Educational Use
Classifier: License :: Free For Home Use
Classifier: Natural Language :: English
Classifier: Programming Language :: Python :: 3.7
Classifier: Programming Language :: Python :: 3.8
Classifier: Programming Language :: Python :: 3.9
Requires-Python: >=3.7
Requires-Dist: pyquora
